opro.py
farsight_opro-0.2.15.dist-info/LICENSE
farsight_opro-0.2.15.dist-info/METADATA
farsight_opro-0.2.15.dist-info/WHEEL
farsight_opro-0.2.15.dist-info/top_level.txt
farsight_opro-0.2.15.dist-info/RECORD
