Metadata-Version: 2.1
Name: farsight-opro
Version: 0.2.15
Summary: Farsight LLM optimizer
Author: Katie Pelton
Classifier: Programming Language :: Python :: 3
Classifier: License :: OSI Approved :: MIT License
Classifier: Operating System :: OS Independent
Requires-Python: >=3.6
License-File: LICENSE
Requires-Dist: openai
Requires-Dist: tqdm
